invenio_records_links/__init__.py
invenio_records_links/config.py
invenio_records_links/ext.py
invenio_records_links/serializers.py
invenio_records_links/version.py
invenio_records_links-1.0.4.dist-info/AUTHORS.rst
invenio_records_links-1.0.4.dist-info/LICENSE
invenio_records_links-1.0.4.dist-info/METADATA
invenio_records_links-1.0.4.dist-info/WHEEL
invenio_records_links-1.0.4.dist-info/entry_points.txt
invenio_records_links-1.0.4.dist-info/top_level.txt
invenio_records_links-1.0.4.dist-info/RECORD
